pyhealthchecks/__init__.py
pyhealthchecks/__version__.py
pyhealthchecks/pyhealthchecks.py
pyhealthchecks-0.3.dist-info/LICENSE.md
pyhealthchecks-0.3.dist-info/METADATA
pyhealthchecks-0.3.dist-info/WHEEL
pyhealthchecks-0.3.dist-info/top_level.txt
pyhealthchecks-0.3.dist-info/RECORD
