Metadata-Version: 2.1
Name: pyhealthchecks
Version: 0.3
Summary: An async client library for ping HealthChecks.io
Home-page: https://github.com/kuchel77/pyhealthchecks
Author: Mark Kuchel
Author-email: mark@kuchel.net
License: UNKNOWN
Platform: UNKNOWN
Classifier: Programming Language :: Python :: 3.6
Classifier: Programming Language :: Python :: 3.7
Classifier: Programming Language :: Python :: 3.8
Classifier: License :: OSI Approved :: Apache Software License
Classifier: Operating System :: OS Independent
Requires-Dist: aiohttp (>=3.5.4)
